README.md
setup.py
pynew/__init__.py
pynew/__main__.py
pynew/config.py
pynew/file_contents.py
pynew/licenses.py
pynew/utils.py
pynew.egg-info/PKG-INFO
pynew.egg-info/SOURCES.txt
pynew.egg-info/dependency_links.txt
pynew.egg-info/entry_points.txt
pynew.egg-info/requires.txt
pynew.egg-info/top_level.txt