Metadata-Version: 1.1
Name: pynew
Version: 0.1.2
Summary: Automate Python project creation
Home-page: https://github.com/cauebs/pynew
Author: Cauê Baasch de Souza
Author-email: cauebs@pm.me
License: MIT
Platform: UNKNOWN
Classifier: Environment :: Console
Classifier: License :: OSI Approved :: MIT License
Classifier: Programming Language :: Python
Classifier: Programming Language :: Python :: 3
Classifier: Programming Language :: Python :: 3.6
Classifier: Programming Language :: Python :: 3.7
Classifier: Programming Language :: Python :: 3 :: Only
